{
    "openapi": "3.0.0",
    "info": {
        "title": "Volvo Cars Api Documentation",
        "description": "Volvo Cars Api Documentation",
        "contact": {
            "name": "Johan Guse",
            "email": "johanguse@gmail.com"
        },
        "license": {
            "name": "Apache 2.0",
            "url": "http://www.apache.org/licenses/LICENSE-2.0.html"
        },
        "version": "1.0.0"
    },
    "servers": [
        {
            "url": "/api/v1"
        }
    ],
    "paths": {
        "/cars": {
            "get": {
                "tags": [
                    "cars"
                ],
                "summary": "Get list of cars",
                "description": "Get list of cars",
                "operationId": "index",
                "parameters": [
                    {
                        "name": "limit",
                        "in": "query",
                        "description": "limit",
                        "required": false,
                        "schema": {
                            "type": "integer"
                        }
                    },
                    {
                        "name": "page",
                        "in": "query",
                        "description": "the page number",
                        "required": false,
                        "schema": {
                            "type": "integer"
                        }
                    },
                    {
                        "name": "order",
                        "in": "query",
                        "description": "order  accepts 'asc' or 'desc'",
                        "required": false,
                        "schema": {
                            "type": "string"
                        }
                    }
                ],
                "responses": {
                    "200": {
                        "description": "Success",
                        "content": {
                            "application/json": {
                                "schema": {
                                    "properties": {
                                        "status": {
                                            "type": "integer",
                                            "example": "200"
                                        },
                                        "data": {
                                            "type": "object"
                                        }
                                    },
                                    "type": "object"
                                }
                            }
                        }
                    }
                }
            }
        },
        "/cars/random": {
            "get": {
                "tags": [
                    "cars"
                ],
                "summary": "Get random cars",
                "description": "Get random cars",
                "operationId": "random",
                "parameters": [
                    {
                        "name": "limit",
                        "in": "query",
                        "description": "limit",
                        "required": false,
                        "schema": {
                            "type": "integer"
                        }
                    },
                    {
                        "name": "page",
                        "in": "query",
                        "description": "the page number",
                        "required": false,
                        "schema": {
                            "type": "integer"
                        }
                    }
                ],
                "responses": {
                    "200": {
                        "description": "Success",
                        "content": {
                            "application/json": {
                                "schema": {
                                    "properties": {
                                        "status": {
                                            "type": "integer",
                                            "example": "200"
                                        },
                                        "data": {
                                            "type": "object"
                                        }
                                    },
                                    "type": "object"
                                }
                            }
                        }
                    }
                }
            }
        }
    }
}